datastore_layer/__init__.py
datastore_layer/models/__init__.py
datastore_layer/models/dated_model_base.py
datastore_layer/models/model_base.py
datastore_layer/models/property_types.py
datastore_layer/models/authentication/__init__.py
datastore_layer/models/authentication/client.py
datastore_layer/models/authentication/grant_type.py
datastore_layer/models/authentication/token.py
datastore_layer/models/bag/__init__.py
datastore_layer/models/bag/bag.py
datastore_layer/models/event/__init__.py
datastore_layer/models/user/__init__.py
datastore_layer/models/user/user.py
datastore_layer/queries/__init__.py
datastore_layer/queries/query_builder.py
datastore_layer-1.12.dist-info/DESCRIPTION.rst
datastore_layer-1.12.dist-info/METADATA
datastore_layer-1.12.dist-info/RECORD
datastore_layer-1.12.dist-info/WHEEL
datastore_layer-1.12.dist-info/metadata.json
datastore_layer-1.12.dist-info/top_level.txt
