Metadata-Version: 2.0
Name: datastore-layer
Version: 1.12
Summary: UNKNOWN
Home-page: UNKNOWN
Author: UNKNOWN
Author-email: UNKNOWN
License: UNKNOWN
Platform: UNKNOWN
Requires-Dist: Werkzeug
